{"tagname":"class","name":"Ext.ux.RowExpander","autodetect":null,"files":[{"filename":"C:/Users/Administrator/Desktop/Ext.JS TS Types Generator v1.3.0/tmp/src-ux/RowExpander.js","linenr":1}],"doc":"\n","aliases":{"widget":null,"request":null},"alternateClassNames":[],"extends":"Ext.grid.plugin.RowExpander","mixins":[],"requires":[],"uses":[],"singleton":null,"private":null,"enum":null,"members":[],"code_type":"ext_define","id":"class-Ext.ux.RowExpander","component":false,"short_doc":" ...","deprecated":{"text":"<p><a href=\"#!/api/Ext.ux.RowExpander\" rel=\"Ext.ux.RowExpander\" class=\"docClass\">Ext.ux.RowExpander</a> has been promoted to the core framework. Use\nExt.grid.plugin.RowExpander instead.</p>\n\n<p><a href=\"#!/api/Ext.ux.RowExpander\" rel=\"Ext.ux.RowExpander\" class=\"docClass\">Ext.ux.RowExpander</a> is now just an empty stub that extends Ext.grid.plugin.RowExpander\nfor backward compatibility reasons.</p>\n","version":"4.0.0"}}